[{"fields": {"date": "2016-12-01T14:42:33.060Z", "player": 76, "score": 3.5}, "model": "questionnaire.game", "pk": 665}, {"fields": {"date": "2016-12-01T14:43:26.543Z", "player": 76, "score": 1.5}, "model": "questionnaire.game", "pk": 666}, {"fields": {"date": "2016-12-01T17:23:34.196Z", "player": 76, "score": null}, "model": "questionnaire.game", "pk": 667}, {"fields": {"date": "2016-12-01T17:23:47.337Z", "player": 76, "score": null}, "model": "questionnaire.game", "pk": 668}, {"fields": {"date": "2016-12-01T17:24:00.640Z", "player": 76, "score": 1.5}, "model": "questionnaire.game", "pk": 669}, {"fields": {"date": "2016-12-01T17:44:21.152Z", "player": 76, "score": 2.5}, "model": "questionnaire.game", "pk": 670}, {"fields": {"date": "2016-12-01T17:47:31.742Z", "player": 76, "score": 1.0}, "model": "questionnaire.game", "pk": 671}, {"fields": {"date": "2016-12-01T20:15:16.633Z", "player": 76, "score": null}, "model": "questionnaire.game", "pk": 672}, {"fields": {"date": "2016-12-01T20:16:52.940Z", "player": 76, "score": null}, "model": "questionnaire.game", "pk": 673}, {"fields": {"date": "2016-12-01T20:18:27.787Z", "player": 76, "score": 2.0}, "model": "questionnaire.game", "pk": 674}, {"fields": {"date": "2016-12-01T20:19:25.746Z", "player": 76, "score": 0.5}, "model": "questionnaire.game", "pk": 675}, {"fields": {"date": "2016-12-01T20:20:23.234Z", "player": 76, "score": null}, "model": "questionnaire.game", "pk": 676}, {"fields": {"date": "2016-12-01T22:15:53.355Z", "player": 76, "score": null}, "model": "questionnaire.game", "pk": 677}][{"fields": {"user_answer": "", "question": 2349, "game": 665, "option4": "temp", "option2": "temp", "option3": "temp", "option1": "temp"}, "model": "questionnaire.answeredquestion", "pk": 3598}, {"fields": {"user_answer": "TRUE", "question": 2492, "game": 665, "option4": "temp", "option2": "temp", "option3": "temp", "option1": "temp"}, "model": "questionnaire.answeredquestion", "pk": 3599}, {"fields": {"user_answer": "NGA", "question": 2469, "game": 665, "option4": "ERI", "option2": "NGA", "option3": "PAK", "option1": "IRQ"}, "model": "questionnaire.answeredquestion", "pk": 3600}, {"fields": {"user_answer": "About 270000", "question": 2317, "game": 665, "option4": "about 100000", "option2": "about 270000", "option3": "about 38500", "option1": "about 435000"}, "model": "questionnaire.answeredquestion", "pk": 3601}, {"fields": {"user_answer": "September", "question": 2436, "game": 665, "option4": "January", "option2": "December", "option3": "September", "option1": "June"}, "model": "questionnaire.answeredquestion", "pk": 3602}, {"fields": {"user_answer": "AFG", "question": 2503, "game": 665, "option4": "PAK", "option2": "SYR", "option3": "SOM", "option1": "AFG"}, "model": "questionnaire.answeredquestion", "pk": 3603}, {"fields": {"user_answer": "TRUE", "question": 2485, "game": 666, "option4": "temp", "option2": "temp", "option3": "temp", "option1": "temp"}, "model": "questionnaire.answeredquestion", "pk": 3604}, {"fields": {"user_answer": "January", "question": 2437, "game": 666, "option4": "May", "option2": "October", "option3": "July", "option1": "January"}, "model": "questionnaire.answeredquestion", "pk": 3605}, {"fields": {"user_answer": "SYR", "question": 2497, "game": 666, "option4": "IRQ", "option2": "JOR", "option3": "IRN", "option1": "SYR"}, "model": "questionnaire.answeredquestion", "pk": 3606}, {"fields": {"user_answer": "Almost half", "question": 2319, "game": 666, "option4": "almost two times higher", "option2": "almost half", "option3": "more than 3 times higher", "option1": "almost the same"}, "model": "questionnaire.answeredquestion", "pk": 3607}, {"fields": {"user_answer": "NGA", "question": 2456, "game": 666, "option4": "SDN", "option2": "NGA", "option3": "GIN", "option1": "SOM"}, "model": "questionnaire.answeredquestion", "pk": 3608}, {"fields": {"user_answer": "", "question": 2340, "game": 666, "option4": "temp", "option2": "temp", "option3": "temp", "option1": "temp"}, "model": "questionnaire.answeredquestion", "pk": 3609}, {"fields": {"user_answer": "", "question": 2439, "game": 667, "option4": "no, it has remained almost constant", "option2": "yes, it has significantly decreased", "option3": "yes, it has more than doubled", "option1": "yes, it has significantly increased"}, "model": "questionnaire.answeredquestion", "pk": 3610}, {"fields": {"user_answer": "", "question": 2470, "game": 667, "option4": "MLI", "option2": "CIV", "option3": "GMB", "option1": "MAR"}, "model": "questionnaire.answeredquestion", "pk": 3611}, {"fields": {"user_answer": "", "question": 2323, "game": 668, "option4": "about 150000", "option2": "about 81000", "option3": "about 420000", "option1": "about 1290000"}, "model": "questionnaire.answeredquestion", "pk": 3612}, {"fields": {"user_answer": "", "question": 2349, "game": 668, "option4": "temp", "option2": "temp", "option3": "temp", "option1": "temp"}, "model": "questionnaire.answeredquestion", "pk": 3613}, {"fields": {"user_answer": "", "question": 2504, "game": 668, "option4": "ZAF", "option2": "USA", "option3": "TUR", "option1": "DEU"}, "model": "questionnaire.answeredquestion", "pk": 3614}, {"fields": {"user_answer": "", "question": 2486, "game": 668, "option4": "temp", "option2": "temp", "option3": "temp", "option1": "temp"}, "model": "questionnaire.answeredquestion", "pk": 3615}, {"fields": {"user_answer": "", "question": 2450, "game": 668, "option4": "no, it has remained almost constant", "option2": "yes, it has almost doubled", "option3": "yes, it has increased by almost 3 times", "option1": "yes, it has increased by almost 5 times"}, "model": "questionnaire.answeredquestion", "pk": 3616}, {"fields": {"user_answer": "", "question": 2471, "game": 668, "option4": "GRC", "option2": "CYP", "option3": "ESP", "option1": "ITA"}, "model": "questionnaire.answeredquestion", "pk": 3617}, {"fields": {"user_answer": "", "question": 2343, "game": 669, "option4": "temp", "option2": "temp", "option3": "temp", "option1": "temp"}, "model": "questionnaire.answeredquestion", "pk": 3618}, {"fields": {"user_answer": "Significantly higher", "question": 2315, "game": 669, "option4": "significantly lower", "option2": "almost the same", "option3": "significantly higher", "option1": "a little bit lower"}, "model": "questionnaire.answeredquestion", "pk": 3619}, {"fields": {"user_answer": "Have increased by almost 80%", "question": 2452, "game": 669, "option4": "have decreased by 10%", "option2": "have increased by almost 80%", "option3": "have remained almost constant", "option1": "have increased by almost 60%"}, "model": "questionnaire.answeredquestion", "pk": 3620}, {"fields": {"user_answer": "FALSE", "question": 2477, "game": 669, "option4": "temp", "option2": "temp", "option3": "temp", "option1": "temp"}, "model": "questionnaire.answeredquestion", "pk": 3621}, {"fields": {"user_answer": "IRN", "question": 2458, "game": 669, "option4": "AFG", "option2": "IRN", "option3": "PAK", "option1": "SYR"}, "model": "questionnaire.answeredquestion", "pk": 3622}, {"fields": {"user_answer": "RUS", "question": 2513, "game": 669, "option4": "USA", "option2": "RUS", "option3": "DEU", "option1": "CHN"}, "model": "questionnaire.answeredquestion", "pk": 3623}, {"fields": {"user_answer": "12", "question": 2344, "game": 670, "option4": "temp", "option2": "temp", "option3": "temp", "option1": "temp"}, "model": "questionnaire.answeredquestion", "pk": 3624}, {"fields": {"user_answer": "About 150000", "question": 2323, "game": 670, "option4": "about 183000", "option2": "about 26100", "option3": "about 150000", "option1": "about 1350000"}, "model": "questionnaire.answeredquestion", "pk": 3625}, {"fields": {"user_answer": "FALSE", "question": 2479, "game": 670, "option4": "temp", "option2": "temp", "option3": "temp", "option1": "temp"}, "model": "questionnaire.answeredquestion", "pk": 3626}, {"fields": {"user_answer": "GBR", "question": 2508, "game": 670, "option4": "NLD", "option2": "NOR", "option3": "GBR", "option1": "DNK"}, "model": "questionnaire.answeredquestion", "pk": 3627}, {"fields": {"user_answer": "ESP", "question": 2463, "game": 670, "option4": "GIB", "option2": "CYP", "option3": "MLT", "option1": "ESP"}, "model": "questionnaire.answeredquestion", "pk": 3628}, {"fields": {"user_answer": "August", "question": 2437, "game": 670, "option4": "May", "option2": "January", "option3": "August", "option1": "July"}, "model": "questionnaire.answeredquestion", "pk": 3629}, {"fields": {"user_answer": "Lebanon, Iran, Afghanistan, Syria", "question": 2321, "game": 671, "option4": "Iran, Afghanistan, Syria, Lebanon", "option2": "Lebanon, Iran, Afghanistan, Syria", "option3": "Syria, Iran, Lebanon, Afghanistan", "option1": "Afghanistan, Lebanon, Syria, Iran"}, "model": "questionnaire.answeredquestion", "pk": 3630}, {"fields": {"user_answer": "Has significantly increased", "question": 2448, "game": 671, "option4": "has remained almost constant", "option2": "has slightly increased", "option3": "has significantly increased", "option1": "has slightly decreased"}, "model": "questionnaire.answeredquestion", "pk": 3631}, {"fields": {"user_answer": "TRUE", "question": 2479, "game": 671, "option4": "temp", "option2": "temp", "option3": "temp", "option1": "temp"}, "model": "questionnaire.answeredquestion", "pk": 3632}, {"fields": {"user_answer": "ESP", "question": 2463, "game": 671, "option4": "CYP", "option2": "GIB", "option3": "ESP", "option1": "MLT"}, "model": "questionnaire.answeredquestion", "pk": 3633}, {"fields": {"user_answer": "", "question": 2335, "game": 671, "option4": "temp", "option2": "temp", "option3": "temp", "option1": "temp"}, "model": "questionnaire.answeredquestion", "pk": 3634}, {"fields": {"user_answer": "UKR", "question": 2502, "game": 671, "option4": "UKR", "option2": "IRQ", "option3": "SYR", "option1": "AFG"}, "model": "questionnaire.answeredquestion", "pk": 3635}, {"fields": {"user_answer": "", "question": 2451, "game": 672, "option4": "67% men, 17% women, 16% children", "option2": "15% men, 55% women, 30% children", "option3": "26% men, 22% women, 52% children", "option1": "51% men, 18% women, 31% children"}, "model": "questionnaire.answeredquestion", "pk": 3636}, {"fields": {"user_answer": "", "question": 2511, "game": 672, "option4": "IRN", "option2": "IRQ", "option3": "AFG", "option1": "PAK"}, "model": "questionnaire.answeredquestion", "pk": 3637}, {"fields": {"user_answer": "", "question": 2320, "game": 672, "option4": "almost one third", "option2": "almost half ", "option3": "almost the double", "option1": "almost the same"}, "model": "questionnaire.answeredquestion", "pk": 3638}, {"fields": {"user_answer": "", "question": 2339, "game": 672, "option4": "temp", "option2": "temp", "option3": "temp", "option1": "temp"}, "model": "questionnaire.answeredquestion", "pk": 3639}, {"fields": {"user_answer": "", "question": 2486, "game": 672, "option4": "temp", "option2": "temp", "option3": "temp", "option1": "temp"}, "model": "questionnaire.answeredquestion", "pk": 3640}, {"fields": {"user_answer": "", "question": 2466, "game": 672, "option4": "TUN", "option2": "EGY", "option3": "LBY", "option1": "DZA"}, "model": "questionnaire.answeredquestion", "pk": 3641}, {"fields": {"user_answer": "", "question": 2514, "game": 673, "option4": "CAN", "option2": "BRA", "option3": "GBR", "option1": "ITA"}, "model": "questionnaire.answeredquestion", "pk": 3642}, {"fields": {"user_answer": "", "question": 2488, "game": 673, "option4": "temp", "option2": "temp", "option3": "temp", "option1": "temp"}, "model": "questionnaire.answeredquestion", "pk": 3643}, {"fields": {"user_answer": "", "question": 2458, "game": 673, "option4": "SYR", "option2": "IRN", "option3": "PAK", "option1": "AFG"}, "model": "questionnaire.answeredquestion", "pk": 3644}, {"fields": {"user_answer": "", "question": 2326, "game": 673, "option4": "about 37.9 million", "option2": "about 49.9 million", "option3": "about 4.9 million", "option1": "about 0.9 million"}, "model": "questionnaire.answeredquestion", "pk": 3645}, {"fields": {"user_answer": "", "question": 2335, "game": 673, "option4": "temp", "option2": "temp", "option3": "temp", "option1": "temp"}, "model": "questionnaire.answeredquestion", "pk": 3646}, {"fields": {"user_answer": "", "question": 2440, "game": 673, "option4": "yes, it has slightly increased", "option2": "yes, it has almost doubled", "option3": "yes, it has slightly decreased", "option1": "no, it has remained almost constant"}, "model": "questionnaire.answeredquestion", "pk": 3647}, {"fields": {"user_answer": "USA", "question": 2504, "game": 674, "option4": "TUR", "option2": "USA", "option3": "DEU", "option1": "ZAF"}, "model": "questionnaire.answeredquestion", "pk": 3648}, {"fields": {"user_answer": "October", "question": 2445, "game": 674, "option4": "June", "option2": "January", "option3": "November", "option1": "October"}, "model": "questionnaire.answeredquestion", "pk": 3649}, {"fields": {"user_answer": "FALSE", "question": 2487, "game": 674, "option4": "temp", "option2": "temp", "option3": "temp", "option1": "temp"}, "model": "questionnaire.answeredquestion", "pk": 3650}, {"fields": {"user_answer": "", "question": 2333, "game": 674, "option4": "9.6 million", "option2": "0.6 million", "option3": "6.6 million", "option1": "4.6 million"}, "model": "questionnaire.answeredquestion", "pk": 3651}, {"fields": {"user_answer": "SYR", "question": 2459, "game": 674, "option4": "IRN", "option2": "SYR", "option3": "IRQ", "option1": "AFG"}, "model": "questionnaire.answeredquestion", "pk": 3652}, {"fields": {"user_answer": "", "question": 2345, "game": 674, "option4": "temp", "option2": "temp", "option3": "temp", "option1": "temp"}, "model": "questionnaire.answeredquestion", "pk": 3653}, {"fields": {"user_answer": "Almost one third", "question": 2320, "game": 675, "option4": "almost the same", "option2": "almost one third", "option3": "almost the double", "option1": "almost half "}, "model": "questionnaire.answeredquestion", "pk": 3654}, {"fields": {"user_answer": "", "question": 2349, "game": 675, "option4": "temp", "option2": "temp", "option3": "temp", "option1": "temp"}, "model": "questionnaire.answeredquestion", "pk": 3655}, {"fields": {"user_answer": "September", "question": 2445, "game": 675, "option4": "October", "option2": "June", "option3": "September", "option1": "July"}, "model": "questionnaire.answeredquestion", "pk": 3656}, {"fields": {"user_answer": "FALSE", "question": 2493, "game": 675, "option4": "temp", "option2": "temp", "option3": "temp", "option1": "temp"}, "model": "questionnaire.answeredquestion", "pk": 3657}, {"fields": {"user_answer": "SYR", "question": 2497, "game": 675, "option4": "IRN", "option2": "IRQ", "option3": "SYR", "option1": "JOR"}, "model": "questionnaire.answeredquestion", "pk": 3658}, {"fields": {"user_answer": "IRQ", "question": 2457, "game": 675, "option4": "AFG", "option2": "IRQ", "option3": "IRN", "option1": "SYR"}, "model": "questionnaire.answeredquestion", "pk": 3659}, {"fields": {"user_answer": "", "question": 2488, "game": 676, "option4": "temp", "option2": "temp", "option3": "temp", "option1": "temp"}, "model": "questionnaire.answeredquestion", "pk": 3660}, {"fields": {"user_answer": "", "question": 2498, "game": 676, "option4": "ITA", "option2": "LBN", "option3": "JOR", "option1": "TUR"}, "model": "questionnaire.answeredquestion", "pk": 3661}, {"fields": {"user_answer": "", "question": 2468, "game": 676, "option4": "ITA", "option2": "GRC", "option3": "CYP", "option1": "ESP"}, "model": "questionnaire.answeredquestion", "pk": 3662}, {"fields": {"user_answer": "", "question": 2446, "game": 676, "option4": "about the 10%", "option2": "about the 20%", "option3": "about the 30%", "option1": "about the 70%"}, "model": "questionnaire.answeredquestion", "pk": 3663}, {"fields": {"user_answer": "", "question": 2327, "game": 676, "option4": "about 2.7 million", "option2": "about 3.7 million", "option3": "about 0.7 million", "option1": "about 15.7 million"}, "model": "questionnaire.answeredquestion", "pk": 3664}, {"fields": {"user_answer": "", "question": 2345, "game": 676, "option4": "temp", "option2": "temp", "option3": "temp", "option1": "temp"}, "model": "questionnaire.answeredquestion", "pk": 3665}, {"fields": {"user_answer": "", "question": 2485, "game": 677, "option4": "temp", "option2": "temp", "option3": "temp", "option1": "temp"}, "model": "questionnaire.answeredquestion", "pk": 3666}, {"fields": {"user_answer": "", "question": 2472, "game": 677, "option4": "CYP", "option2": "MLT", "option3": "GRC", "option1": "ITA"}, "model": "questionnaire.answeredquestion", "pk": 3667}, {"fields": {"user_answer": "", "question": 2509, "game": 677, "option4": "RUS", "option2": "DEU", "option3": "USA", "option1": "CHN"}, "model": "questionnaire.answeredquestion", "pk": 3668}, {"fields": {"user_answer": "", "question": 2453, "game": 677, "option4": "23%", "option2": "108%", "option3": "71%", "option1": "19%"}, "model": "questionnaire.answeredquestion", "pk": 3669}, {"fields": {"user_answer": "", "question": 2315, "game": 677, "option4": "a little bit lower", "option2": "significantly lower", "option3": "almost the same", "option1": "significantly higher"}, "model": "questionnaire.answeredquestion", "pk": 3670}, {"fields": {"user_answer": "", "question": 2336, "game": 677, "option4": "temp", "option2": "temp", "option3": "temp", "option1": "temp"}, "model": "questionnaire.answeredquestion", "pk": 3671}]